XStatic_jQuery_File_Upload-10.31.0.1-py3.13-nspkg.pth
xstatic/pkg/jquery_file_upload/__init__.py
xstatic/pkg/jquery_file_upload/data/css/jquery.fileupload-noscript.css
xstatic/pkg/jquery_file_upload/data/css/jquery.fileupload-ui-noscript.css
xstatic/pkg/jquery_file_upload/data/css/jquery.fileupload-ui.css
xstatic/pkg/jquery_file_upload/data/css/jquery.fileupload.css
xstatic/pkg/jquery_file_upload/data/img/loading.gif
xstatic/pkg/jquery_file_upload/data/img/progressbar.gif
xstatic/pkg/jquery_file_upload/data/js/jquery.fileupload-audio.js
xstatic/pkg/jquery_file_upload/data/js/jquery.fileupload-image.js
xstatic/pkg/jquery_file_upload/data/js/jquery.fileupload-process.js
xstatic/pkg/jquery_file_upload/data/js/jquery.fileupload-ui.js
xstatic/pkg/jquery_file_upload/data/js/jquery.fileupload-validate.js
xstatic/pkg/jquery_file_upload/data/js/jquery.fileupload-video.js
xstatic/pkg/jquery_file_upload/data/js/jquery.fileupload.js
xstatic/pkg/jquery_file_upload/data/js/jquery.iframe-transport.js
xstatic/pkg/jquery_file_upload/data/js/cors/jquery.postmessage-transport.js
xstatic/pkg/jquery_file_upload/data/js/cors/jquery.xdr-transport.js
xstatic/pkg/jquery_file_upload/data/js/vendor/jquery.ui.widget.js
xstatic_jquery_file_upload-10.31.0.1.dist-info/METADATA
xstatic_jquery_file_upload-10.31.0.1.dist-info/WHEEL
xstatic_jquery_file_upload-10.31.0.1.dist-info/namespace_packages.txt
xstatic_jquery_file_upload-10.31.0.1.dist-info/top_level.txt
xstatic_jquery_file_upload-10.31.0.1.dist-info/RECORD
