Metadata-Version: 2.4
Name: XStatic-jQuery-File-Upload
Version: 10.31.0.1
Summary: jQuery-File-Upload 10.31.0 (XStatic packaging standard)
Home-page: https://github.com/blueimp/jQuery-File-Upload
Maintainer: Thomas Waldmann
Maintainer-email: tw@waldmann-edv.de
License: (same as jQuery-File-Upload)
Keywords: jquery_file_upload xstatic
Platform: any
Dynamic: description
Dynamic: home-page
Dynamic: keywords
Dynamic: license
Dynamic: maintainer
Dynamic: maintainer-email
Dynamic: platform
Dynamic: summary
